{
  "action": {
    "description": "First read in House and referral to committee waived pursuant to JR 6D-1 H.J. 485",
    "occurred_at": "2026-03-03",
    "jurisdiction_id": "~{\"classification\": \"lower\"}",
    "session_id": "2026",
    "entity_type": "bill",
    "classifications": [
      "introduction",
      "reading-1"
    ],
    "related_entities": [],
    "sources": [
      {
        "url": "https://sdlegislature.gov/Session/Bill/27086",
        "note": ""
      },
      {
        "url": "https://sdlegislature.gov/api/Bills/27086",
        "note": ""
      }
    ]
  },
  "bill_id": "SB 136"
}