{
  "action": {
    "description": "Signed by the President S.J. 236",
    "occurred_at": "2026-02-10",
    "jurisdiction_id": "~{\"classification\": \"upper\"}",
    "session_id": "2026",
    "entity_type": "bill",
    "classifications": [
      "passage"
    ],
    "related_entities": [],
    "sources": [
      {
        "url": "https://sdlegislature.gov/Session/Bill/26852",
        "note": ""
      },
      {
        "url": "https://sdlegislature.gov/api/Bills/26852",
        "note": ""
      }
    ]
  },
  "bill_id": "SB 53"
}