{
  "identifier": "",
  "motion_text": "Do Pass",
  "motion_classification": [
    "passage"
  ],
  "start_date": "2026-02-20",
  "result": "pass",
  "organization": "~{\"classification\": \"upper\"}",
  "legislative_session": "2026",
  "bill": "51a6161c-75d6-11f1-abda-e227e47b00f9",
  "bill_action": null,
  "bill_identifier": "HB 1056",
  "votes": [
    {
      "option": "yes",
      "voter_name": "Miskimins",
      "voter_id": "~{\"name\": \"Miskimins\"}",
      "note": ""
    },
    {
      "option": "yes",
      "voter_name": "Vilhauer",
      "voter_id": "~{\"name\": \"Vilhauer\"}",
      "note": ""
    },
    {
      "option": "absent",
      "voter_name": "Carley",
      "voter_id": "~{\"name\": \"Carley\"}",
      "note": ""
    },
    {
      "option": "yes",
      "voter_name": "Voita",
      "voter_id": "~{\"name\": \"Voita\"}",
      "note": ""
    },
    {
      "option": "yes",
      "voter_name": "Howard",
      "voter_id": "~{\"name\": \"Howard\"}",
      "note": ""
    },
    {
      "option": "yes",
      "voter_name": "Foster",
      "voter_id": "~{\"name\": \"Foster\"}",
      "note": ""
    },
    {
      "option": "yes",
      "voter_name": "Zikmund",
      "voter_id": "~{\"name\": \"Zikmund\"}",
      "note": ""
    },
    {
      "option": "no",
      "voter_name": "Lapka",
      "voter_id": "~{\"name\": \"Lapka\"}",
      "note": ""
    },
    {
      "option": "no",
      "voter_name": "Otten",
      "voter_id": "~{\"name\": \"Otten\"}",
      "note": ""
    }
  ],
  "counts": [
    {
      "option": "yes",
      "value": 6
    },
    {
      "option": "no",
      "value": 2
    },
    {
      "option": "excused",
      "value": 0
    },
    {
      "option": "absent",
      "value": 1
    }
  ],
  "sources": [
    {
      "url": "https://sdlegislature.gov/api/Votes/83959",
      "note": ""
    }
  ],
  "extras": {},
  "dedupe_key": "https://sdlegislature.gov/api/Votes/83959"
}