{
  "action": {
    "description": "Senate Do Pass Amended , Passed, YEAS 27, NAYS 7 S.J. 184",
    "occurred_at": "2026-02-04",
    "jurisdiction_id": "~{\"classification\": \"upper\"}",
    "session_id": "2026",
    "entity_type": "bill",
    "classifications": [],
    "related_entities": [],
    "sources": [
      {
        "url": "https://sdlegislature.gov/Session/Bill/26703",
        "note": ""
      },
      {
        "url": "https://sdlegislature.gov/api/Bills/26703",
        "note": ""
      }
    ]
  },
  "bill_id": "SB 89"
}