{
  "legislative_session": "2026",
  "identifier": "HB 1103",
  "title": "require that annual withdrawal of groundwater from any groundwater source may not exceed the annual recharge of water to the groundwater source.",
  "from_organization": "~{\"classification\": \"lower\"}",
  "classification": [
    "bill"
  ],
  "subject": [
    "Water Management",
    "Water Rights"
  ],
  "abstracts": [],
  "other_titles": [],
  "other_identifiers": [
    {
      "identifier": "ocd-bill-sd-2026-hb1103"
    }
  ],
  "actions": [
    {
      "description": "First read in House and referred to House Agriculture and Natural Resources H.J. 103",
      "date": "2026-01-21",
      "organization_id": "~{\"classification\": \"lower\"}",
      "classification": [
        "introduction",
        "reading-1",
        "referral-committee"
      ],
      "related_entities": [],
      "_processing": {
        "log_file_created": "2026-07-13T06:07:04Z"
      }
    },
    {
      "description": "Scheduled for hearing H.J. 1",
      "date": "2026-01-29",
      "organization_id": "~{\"classification\": \"lower\"}",
      "classification": [],
      "related_entities": [],
      "_processing": {
        "log_file_created": "2026-07-13T06:07:04Z"
      }
    },
    {
      "description": "Agriculture and Natural Resources Do Pass , Passed, YEAS 9, NAYS 4 H.J. 11",
      "date": "2026-01-29",
      "organization_id": "~{\"classification\": \"lower\"}",
      "classification": [
        "committee-passage"
      ],
      "related_entities": [],
      "_processing": {
        "log_file_created": "2026-07-13T06:07:04Z"
      }
    },
    {
      "description": "House of Representatives Motion to amend , Passed, H.J. 197 Amendment 1103A",
      "date": "2026-02-02",
      "organization_id": "~{\"classification\": \"lower\"}",
      "classification": [
        "amendment-introduction",
        "amendment-passage"
      ],
      "related_entities": [],
      "_processing": {
        "log_file_created": "2026-07-13T06:07:04Z"
      }
    },
    {
      "description": "House of Representatives Do Pass Amended , Passed, YEAS 16, NAYS 49 H.J. 197",
      "date": "2026-02-02",
      "organization_id": "~{\"classification\": \"lower\"}",
      "classification": [],
      "related_entities": [],
      "_processing": {
        "log_file_created": "2026-07-13T06:07:04Z"
      }
    }
  ],
  "sponsorships": [
    {
      "name": "Odenbach",
      "classification": "primary",
      "entity_type": "person",
      "primary": true,
      "person_id": "~{\"chamber\": \"lower\", \"name\": \"Odenbach\"}",
      "organization_id": null
    },
    {
      "name": "Baxter",
      "classification": "primary",
      "entity_type": "person",
      "primary": true,
      "person_id": "~{\"chamber\": \"lower\", \"name\": \"Baxter\"}",
      "organization_id": null
    },
    {
      "name": "Foster",
      "classification": "primary",
      "entity_type": "person",
      "primary": true,
      "person_id": "~{\"chamber\": \"upper\", \"name\": \"Foster\"}",
      "organization_id": null
    },
    {
      "name": "Howard",
      "classification": "primary",
      "entity_type": "person",
      "primary": true,
      "person_id": "~{\"chamber\": \"upper\", \"name\": \"Howard\"}",
      "organization_id": null
    },
    {
      "name": "Karr",
      "classification": "primary",
      "entity_type": "person",
      "primary": true,
      "person_id": "~{\"chamber\": \"upper\", \"name\": \"Karr\"}",
      "organization_id": null
    },
    {
      "name": "Perry",
      "classification": "primary",
      "entity_type": "person",
      "primary": true,
      "person_id": "~{\"chamber\": \"upper\", \"name\": \"Perry\"}",
      "organization_id": null
    }
  ],
  "related_bills": [],
  "versions": [
    {
      "note": "Introduced",
      "links": [
        {
          "url": "https://sdlegislature.gov/Session/Bill/26783/295879",
          "media_type": "text/html"
        },
        {
          "url": "https://mylrc.sdlegislature.gov/api/Documents/295879.pdf",
          "media_type": "application/pdf"
        }
      ],
      "date": "2026-01-21",
      "classification": ""
    },
    {
      "note": "1103A",
      "links": [
        {
          "url": "https://mylrc.sdlegislature.gov/api/Documents/299913.pdf",
          "media_type": "application/pdf"
        }
      ],
      "date": "",
      "classification": ""
    }
  ],
  "documents": [],
  "citations": [],
  "sources": [
    {
      "url": "https://sdlegislature.gov/Session/Bill/26783",
      "note": ""
    },
    {
      "url": "https://sdlegislature.gov/api/Bills/26783",
      "note": ""
    }
  ],
  "extras": {},
  "jurisdiction": {
    "id": "ocd-jurisdiction/country:us/state:sd/government",
    "name": "South Dakota",
    "classification": "state",
    "division_id": "ocd-division/country:us/state:sd"
  },
  "_processing": {
    "logs_latest_update": "2026-07-13T06:07:04Z",
    "text_extraction_latest_update": "2026-07-13T10:29:03.515246Z"
  }
}