{
  "legislative_session": "2026",
  "identifier": "HCR 6001",
  "title": "urging the United States Department of Homeland Security to establish a tribal law enforcement training academy in South Dakota.",
  "from_organization": "~{\"classification\": \"lower\"}",
  "classification": [
    "concurrent resolution"
  ],
  "subject": [
    "House Concurrent Resolution",
    "Indian Tribes",
    "Interim Legislative Committee Bill",
    "Law Enforcement"
  ],
  "abstracts": [],
  "other_titles": [],
  "other_identifiers": [
    {
      "identifier": "ocd-bill-sd-2026-hcr6001"
    }
  ],
  "actions": [
    {
      "description": "First read in House and referred to House Judiciary H.J. 10",
      "date": "2026-01-13",
      "organization_id": "~{\"classification\": \"lower\"}",
      "classification": [
        "introduction",
        "reading-1",
        "referral-committee"
      ],
      "related_entities": [],
      "_processing": {
        "log_file_created": "2026-07-13T06:07:04Z"
      }
    },
    {
      "description": "Scheduled for hearing",
      "date": "2026-01-23",
      "organization_id": "~{\"classification\": \"lower\"}",
      "classification": [],
      "related_entities": [],
      "_processing": {
        "log_file_created": "2026-07-13T06:07:04Z"
      }
    },
    {
      "description": "Judiciary Motion to amend , Passed, Amendment HCR6001A",
      "date": "2026-01-23",
      "organization_id": "~{\"classification\": \"lower\"}",
      "classification": [
        "amendment-introduction",
        "amendment-passage"
      ],
      "related_entities": [],
      "_processing": {
        "log_file_created": "2026-07-13T06:07:04Z"
      }
    },
    {
      "description": "Judiciary Do Pass Amended , Passed, YEAS 13, NAYS 0",
      "date": "2026-01-23",
      "organization_id": "~{\"classification\": \"lower\"}",
      "classification": [],
      "related_entities": [],
      "_processing": {
        "log_file_created": "2026-07-13T06:07:04Z"
      }
    },
    {
      "description": "Certified uncontested, placed on consent , Passed,",
      "date": "2026-01-23",
      "organization_id": "~{\"classification\": \"lower\"}",
      "classification": [],
      "related_entities": [],
      "_processing": {
        "log_file_created": "2026-07-13T06:07:04Z"
      }
    },
    {
      "description": "Remove from Consent Calendar H.J. 151",
      "date": "2026-01-27",
      "organization_id": "~{\"classification\": \"lower\"}",
      "classification": [],
      "related_entities": [],
      "_processing": {
        "log_file_created": "2026-07-13T06:07:04Z"
      }
    },
    {
      "description": "House of Representatives Adopt Resolution as amended , Passed, YEAS 49, NAYS 18 H.J. 162",
      "date": "2026-01-28",
      "organization_id": "~{\"classification\": \"lower\"}",
      "classification": [],
      "related_entities": [],
      "_processing": {
        "log_file_created": "2026-07-13T06:07:04Z"
      }
    },
    {
      "description": "First read in Senate and referral to committee waived pursuant to JR 6D-1 S.J. 137",
      "date": "2026-01-29",
      "organization_id": "~{\"classification\": \"upper\"}",
      "classification": [
        "introduction",
        "reading-1"
      ],
      "related_entities": [],
      "_processing": {
        "log_file_created": "2026-07-13T06:07:04Z"
      }
    },
    {
      "description": "Senate Motion to amend resolution , Passed, S.J. 158",
      "date": "2026-02-02",
      "organization_id": "~{\"classification\": \"upper\"}",
      "classification": [],
      "related_entities": [],
      "_processing": {
        "log_file_created": "2026-07-13T06:07:04Z"
      }
    },
    {
      "description": "Senate Concurred in Resolution as Amended , Passed, YEAS 32, NAYS 2 S.J. 158",
      "date": "2026-02-02",
      "organization_id": "~{\"classification\": \"upper\"}",
      "classification": [],
      "related_entities": [],
      "_processing": {
        "log_file_created": "2026-07-13T06:07:04Z"
      }
    },
    {
      "description": "House of Representatives Concurred in amendments , Passed, YEAS 69, NAYS 0 H.J. 216",
      "date": "2026-02-04",
      "organization_id": "~{\"classification\": \"upper\"}",
      "classification": [],
      "related_entities": [],
      "_processing": {
        "log_file_created": "2026-07-13T06:07:04Z"
      }
    }
  ],
  "sponsorships": [
    {
      "name": "Emery",
      "classification": "primary",
      "entity_type": "person",
      "primary": true,
      "person_id": "~{\"chamber\": \"lower\", \"name\": \"Emery\"}",
      "organization_id": null
    },
    {
      "name": "Smith",
      "classification": "primary",
      "entity_type": "person",
      "primary": true,
      "person_id": "~{\"chamber\": \"upper\", \"name\": \"Smith\"}",
      "organization_id": null
    },
    {
      "name": "Mortenson",
      "classification": "primary",
      "entity_type": "person",
      "primary": true,
      "person_id": "~{\"chamber\": \"lower\", \"name\": \"Mortenson\"}",
      "organization_id": null
    },
    {
      "name": "Pourier",
      "classification": "primary",
      "entity_type": "person",
      "primary": true,
      "person_id": "~{\"chamber\": \"lower\", \"name\": \"Pourier\"}",
      "organization_id": null
    }
  ],
  "related_bills": [],
  "versions": [
    {
      "note": "Introduced",
      "links": [
        {
          "url": "https://sdlegislature.gov/Session/Bill/26511/291572",
          "media_type": "text/html"
        },
        {
          "url": "https://mylrc.sdlegislature.gov/api/Documents/291572.pdf",
          "media_type": "application/pdf"
        }
      ],
      "date": "2025-12-26",
      "classification": ""
    },
    {
      "note": "House Judiciary Engrossed",
      "links": [
        {
          "url": "https://sdlegislature.gov/Session/Bill/26511/296883",
          "media_type": "text/html"
        },
        {
          "url": "https://mylrc.sdlegislature.gov/api/Documents/296883.pdf",
          "media_type": "application/pdf"
        }
      ],
      "date": "2026-01-23",
      "classification": ""
    },
    {
      "note": "Senate Engrossed",
      "links": [
        {
          "url": "https://sdlegislature.gov/Session/Bill/26511/300180",
          "media_type": "text/html"
        },
        {
          "url": "https://mylrc.sdlegislature.gov/api/Documents/300180.pdf",
          "media_type": "application/pdf"
        }
      ],
      "date": "2026-02-02",
      "classification": ""
    },
    {
      "note": "Enrolled",
      "links": [
        {
          "url": "https://sdlegislature.gov/Session/Bill/26511/301474",
          "media_type": "text/html"
        },
        {
          "url": "https://mylrc.sdlegislature.gov/api/Documents/301474.pdf",
          "media_type": "application/pdf"
        }
      ],
      "date": "2026-02-05",
      "classification": ""
    },
    {
      "note": "HCR6001A",
      "links": [
        {
          "url": "https://mylrc.sdlegislature.gov/api/Documents/296751.pdf",
          "media_type": "application/pdf"
        }
      ],
      "date": "",
      "classification": ""
    }
  ],
  "documents": [],
  "citations": [],
  "sources": [
    {
      "url": "https://sdlegislature.gov/Session/Bill/26511",
      "note": ""
    },
    {
      "url": "https://sdlegislature.gov/api/Bills/26511",
      "note": ""
    }
  ],
  "extras": {},
  "jurisdiction": {
    "id": "ocd-jurisdiction/country:us/state:sd/government",
    "name": "South Dakota",
    "classification": "state",
    "division_id": "ocd-division/country:us/state:sd"
  },
  "_processing": {
    "logs_latest_update": "2026-07-13T06:07:04Z",
    "text_extraction_latest_update": "2026-07-13T10:52:23.543736Z"
  }
}